{
  "required": true,
  "package": "com.hexagram2021.emeraldcraft.mixin",
  "compatibilityLevel": "JAVA_8",
  "refmap": "emeraldcraft.refmap.json",
  "mixins": [
	"AbstractPiglinEntityMixin",
	"AbstractSkeletonMixin",
	"BlockEntityTypeAccess",
	"EntityActionPacketActionMixin",
	"HeroGiftsTaskAccess",
	"MobEntityMixin",
	"MultiNoiseBiomeSourceAccess",
	"NetherBiomesAccess",
	"PhantomEntityMixin",
	"PiglinAiMixin",
	"PiglinBruteAiMixin",
	"RecipeBookCategoryMixin",
	"RecipeBookStatusMixin",
	"ServerPlayNetHandlerMixin",
	"SingleJigsawAccess",
	"VillagePoolsMixin",
	"ZombieEntityMixin",
	"ZombifiedPiglinEntityMixin"
  ],
  "minVersion": "0.8",
  "client": [
	"ClientRecipeBookMixin",
	"LocalPlayerMixin",
	"RecipeBookCategoriesMixin"
  ]
}
